hive/messaging/__init__.py
hive/messaging/__version__.py
hive/messaging/channel.py
hive/messaging/connection.py
hive/messaging/message.py
hive/messaging/message_bus.py
hive/messaging/publisher.py
hive/messaging/py.typed
hive/messaging/semantics.py
hive/messaging/testing.py
hive/messaging/typing.py
hive_messaging-0.16.5.dist-info/METADATA
hive_messaging-0.16.5.dist-info/WHEEL
hive_messaging-0.16.5.dist-info/top_level.txt
hive_messaging-0.16.5.dist-info/RECORD
