Metadata-Version: 2.4
Name: hive-messaging
Version: 0.16.5
Summary: Messaging layer for Hive
Author-email: Gary Benson <gary@gbenson.net>
License-Expression: MIT
Project-URL: Homepage, https://github.com/gbenson/hive/tree/main/libs/messaging
Project-URL: Source, https://github.com/gbenson/hive
Requires-Dist: cloudevents[pydantic]
Requires-Dist: contenttype
Requires-Dist: hive-common>=0.3.5
Requires-Dist: pika
Requires-Dist: typing-extensions
